eu4ng/__init__.py
eu4ng/function.py
eu4ng_function-1.0.0.0.dist-info/METADATA
eu4ng_function-1.0.0.0.dist-info/WHEEL
eu4ng_function-1.0.0.0.dist-info/top_level.txt
eu4ng_function-1.0.0.0.dist-info/RECORD
