Metadata-Version: 2.1
Name: eu4ng-function
Version: 1.0.0.0
Summary: Personal Function Package for Eu4ng
Home-page: https://eu4ng.tistory.com
Author: Eu4ng
Author-email: wjdgnsehowl@naver.com
License: MIT
Platform: UNKNOWN
Requires-Python: >=3
